oasm/flex/__init__.py
oasm_flex-0.1.3.dist-info/METADATA
oasm_flex-0.1.3.dist-info/WHEEL
oasm_flex-0.1.3.dist-info/top_level.txt
oasm_flex-0.1.3.dist-info/RECORD
